easyocr_window_scanner/LICENSE
easyocr_window_scanner/README.MD
easyocr_window_scanner/__init__.py
easyocr_window_scanner/requirements.txt
easyocr_window_scanner/thirdparty.json
easyocr_window_scanner-0.10.dist-info/LICENSE.rst
easyocr_window_scanner-0.10.dist-info/METADATA
easyocr_window_scanner-0.10.dist-info/WHEEL
easyocr_window_scanner-0.10.dist-info/top_level.txt
easyocr_window_scanner-0.10.dist-info/RECORD
