Metadata-Version: 2.1
Name: easyocr-window-scanner
Version: 0.10
Summary: OCR on screenshots with EasyOCR - Windows only
Home-page: https://github.com/hansalemaos/easyocr_window_scanner
Author: Johannes Fischer
Author-email: <aulasparticularesdealemaosp@gmail.com>
License: MIT
Keywords: screenshot,adb,windows,hwnd,handle,bot,EasyOCR
Classifier: Development Status :: 4 - Beta
Classifier: Programming Language :: Python :: 3 :: Only
Classifier: Programming Language :: Python :: 3.9
Classifier: Topic :: Scientific/Engineering :: Visualization
Classifier: Topic :: Software Development :: Libraries :: Python Modules
Classifier: Topic :: Text Editors :: Text Processing
Classifier: Topic :: Text Processing :: General
Classifier: Topic :: Text Processing :: Indexing
Classifier: Topic :: Text Processing :: Filters
Classifier: Topic :: Utilities
License-File: LICENSE.rst
Requires-Dist: a-cv2-imshow-thread
Requires-Dist: a-pandas-ex-plode-tool
Requires-Dist: easyocr
Requires-Dist: keyboard
Requires-Dist: numpy
Requires-Dist: opencv-python
Requires-Dist: pandas
Requires-Dist: requests
Requires-Dist: windows-adb-screen-capture
